{
  "format_version": "moves-snapshot/v1",
  "name": "db__movesexecution1ccc0233_campuscluster_illinois_edu__samplevehiclesoaking",
  "schema": [
    {
      "name": "soakDayID",
      "kind": "int64"
    },
    {
      "name": "sourceTypeID",
      "kind": "int64"
    },
    {
      "name": "dayID",
      "kind": "int64"
    },
    {
      "name": "hourID",
      "kind": "int64"
    },
    {
      "name": "soakFraction",
      "kind": "float64"
    }
  ],
  "natural_key": [
    "soakDayID",
    "sourceTypeID",
    "dayID",
    "hourID"
  ],
  "row_count": 0,
  "float_decimals": 12,
  "content_sha256": "fe829d542b3adbda6983438bf5c654fc3dbbd3b645a06dff73b3bf5fbce1b25e"
}
