{
  "format_version": "moves-snapshot/v1",
  "name": "db__out_process_pm_exhaust__movestablesused",
  "schema": [
    {
      "name": "MOVESRunID",
      "kind": "int64"
    },
    {
      "name": "databaseServer",
      "kind": "utf8"
    },
    {
      "name": "databaseName",
      "kind": "utf8"
    },
    {
      "name": "tableName",
      "kind": "utf8"
    },
    {
      "name": "dataFileSize",
      "kind": "int64"
    },
    {
      "name": "dataFileModificationDate",
      "kind": "utf8"
    },
    {
      "name": "tableUseSequence",
      "kind": "int64"
    }
  ],
  "natural_key": [],
  "row_count": 143,
  "float_decimals": 12,
  "content_sha256": "874f6f1a10f28f852effcff08f293da63ab79ff00e2c3d09ef0eda6707dd1269"
}
