{
  "format_version": "moves-snapshot/v1",
  "name": "db__movesexecution1ccc0232_campuscluster_illinois_edu__methanethcratio",
  "schema": [
    {
      "name": "processID",
      "kind": "int64"
    },
    {
      "name": "fuelSubtypeID",
      "kind": "int64"
    },
    {
      "name": "regClassID",
      "kind": "int64"
    },
    {
      "name": "beginModelYearID",
      "kind": "int64"
    },
    {
      "name": "endModelYearID",
      "kind": "int64"
    },
    {
      "name": "CH4THCRatio",
      "kind": "float64"
    },
    {
      "name": "dataSourceID",
      "kind": "int64"
    }
  ],
  "natural_key": [
    "processID",
    "fuelSubtypeID",
    "regClassID",
    "beginModelYearID",
    "endModelYearID"
  ],
  "row_count": 338,
  "float_decimals": 12,
  "content_sha256": "cedc200eb85a71e7f38125dfac4d5443967731e0ddeb4261e2f0fc3ecdefca96"
}
