{
  "format_version": "moves-snapshot/v1",
  "name": "db__movesexecution1ccc0232_campuscluster_illinois_edu__neededfuelsupply",
  "schema": [
    {
      "name": "fuelRegionID",
      "kind": "int64"
    },
    {
      "name": "fuelYearID",
      "kind": "int64"
    },
    {
      "name": "monthGroupID",
      "kind": "int64"
    },
    {
      "name": "fuelTypeID",
      "kind": "int64"
    },
    {
      "name": "defaultFormulationID",
      "kind": "int64"
    }
  ],
  "natural_key": [
    "fuelRegionID",
    "fuelYearID",
    "monthGroupID",
    "fuelTypeID"
  ],
  "row_count": 4,
  "float_decimals": 12,
  "content_sha256": "66d3cd4148ec9d1c2556ec097afccc60d32578514055269dc375d6330307db79"
}
